{
  "unversionedId": "mttr/stakingcore",
  "id": "mttr/stakingcore",
  "isDocsHomePage": false,
  "title": "Staking",
  "description": "Active Farms",
  "source": "@site/docs/mttr/stakingcore.md",
  "sourceDirName": "mttr",
  "slug": "/stakingcore",
  "permalink": "/stakingcore",
  "version": "current",
  "sidebarPosition": 5,
  "frontMatter": {
    "sidebar_position": 5,
    "slug": "/stakingcore"
  },
  "sidebar": "tutorialSidebar",
  "previous": {
    "title": "Selecting a Theme",
    "permalink": "/selecting-theme"
  },
  "next": {
    "title": "Unstaking",
    "permalink": "/unstakingcore"
  }
}